approx_pi/__init__.py
approx_pi/pi_approx.py
approx_pi-0.1.1.dist-info/WHEEL
approx_pi-0.1.1.dist-info/METADATA
approx_pi-0.1.1.dist-info/RECORD
